qwikfire/__init__.py
qwikfire/qwikfire.py
qwikfire-0.1.3.dist-info/LICENSE
qwikfire-0.1.3.dist-info/METADATA
qwikfire-0.1.3.dist-info/WHEEL
qwikfire-0.1.3.dist-info/RECORD
