Metadata-Version: 2.1
Name: qwikfire
Version: 0.1.3
Summary: Decorate class methods with shell commands
Home-page: https://github.com/akarasulu/qwikfire
Author: Alex O. Karasulu
Author-email: akarasulu@gmail.com
Requires-Python: >=3.11,<4.0
Classifier: Programming Language :: Python :: 3
Classifier: Programming Language :: Python :: 3.11
Classifier: Programming Language :: Python :: 3.12
Classifier: Programming Language :: Python :: 3.13
Requires-Dist: sh (>=2.1.0,<3.0.0)
Project-URL: Documentation, https://akarasulu.github.io/qwikfire/
Project-URL: Repository, https://github.com/akarasulu/qwikfire
